linux_gui/__init__.py
linux_gui/constants.py
linux_gui/gui_logger.py
linux_gui/indicator.py
linux_gui/protonvpn_gui.py
linux_gui/utils.py
linux_gui/presenters/__init__.py
linux_gui/presenters/dashboard_presenter.py
linux_gui/presenters/login_presenter.py
linux_gui/presenters/settings_presenter.py
linux_gui/resources/__init__.py
linux_gui/resources/img/flags/__init__.py
linux_gui/resources/img/flags/large/__init__.py
linux_gui/resources/img/flags/large/ad.jpg
linux_gui/resources/img/flags/large/ae.jpg
linux_gui/resources/img/flags/large/af.jpg
linux_gui/resources/img/flags/large/ag.jpg
linux_gui/resources/img/flags/large/al.jpg
linux_gui/resources/img/flags/large/am.jpg
linux_gui/resources/img/flags/large/ao.jpg
linux_gui/resources/img/flags/large/ar.jpg
linux_gui/resources/img/flags/large/at.jpg
linux_gui/resources/img/flags/large/au.jpg
linux_gui/resources/img/flags/large/az.jpg
linux_gui/resources/img/flags/large/ba.jpg
linux_gui/resources/img/flags/large/bb.jpg
linux_gui/resources/img/flags/large/bd.jpg
linux_gui/resources/img/flags/large/be.jpg
linux_gui/resources/img/flags/large/bf.jpg
linux_gui/resources/img/flags/large/bg.jpg
linux_gui/resources/img/flags/large/bh.jpg
linux_gui/resources/img/flags/large/bi.jpg
linux_gui/resources/img/flags/large/bj.jpg
linux_gui/resources/img/flags/large/bn.jpg
linux_gui/resources/img/flags/large/bo.jpg
linux_gui/resources/img/flags/large/br.jpg
linux_gui/resources/img/flags/large/bs.jpg
linux_gui/resources/img/flags/large/bt.jpg
linux_gui/resources/img/flags/large/bw.jpg
linux_gui/resources/img/flags/large/by.jpg
linux_gui/resources/img/flags/large/bz.jpg
linux_gui/resources/img/flags/large/ca.jpg
linux_gui/resources/img/flags/large/cd.jpg
linux_gui/resources/img/flags/large/cf.jpg
linux_gui/resources/img/flags/large/cg.jpg
linux_gui/resources/img/flags/large/ch.jpg
linux_gui/resources/img/flags/large/ci.jpg
linux_gui/resources/img/flags/large/ck.jpg
linux_gui/resources/img/flags/large/cl.jpg
protonvpn_gui-2.1.1.dist-info/AUTHORS.md
protonvpn_gui-2.1.1.dist-info/LICENSE
protonvpn_gui-2.1.1.dist-info/METADATA
protonvpn_gui-2.1.1.dist-info/WHEEL
protonvpn_gui-2.1.1.dist-info/entry_points.txt
protonvpn_gui-2.1.1.dist-info/top_level.txt
protonvpn_gui-2.1.1.dist-info/RECORD
