Metadata-Version: 2.1
Name: protonvpn-gui
Version: 2.1.1
Summary: Linux GUI client for ProtonVPN
Home-page: https://github.com/ProtonVPN/linux-gui
Author: Proton Technologies AG
Author-email: contact@protonvpn.com
License: GPLv3
Platform: UNKNOWN
Classifier: Development Status :: 4 - Beta
Classifier: Environment :: Console
Classifier: Environment :: X11 Applications :: GTK
Classifier: Intended Audience :: End Users/Desktop
Classifier: Operating System :: POSIX :: Linux
Classifier: License :: OSI Approved :: GNU General Public License v3 (GPLv3)
Classifier: Programming Language :: Python
Classifier: Programming Language :: Python :: 3 :: Only
Classifier: Programming Language :: Python :: 3.5
Classifier: Programming Language :: Python :: 3.6
Classifier: Programming Language :: Python :: 3.7
Classifier: Programming Language :: Python :: 3.8
Requires-Python: >=3.5
Requires-Dist: protonvpn-cli (>=2.2.2)
Requires-Dist: requests (>=2.23.0)
